sop_migration/__init__.py
sop_migration/filtersets.py
sop_migration/forms.py
sop_migration/models.py
sop_migration/navigation.py
sop_migration/search.py
sop_migration/tables.py
sop_migration/template_content.py
sop_migration/urls.py
sop_migration/views.py
sop_migration/api/__init__.py
sop_migration/api/serializers.py
sop_migration/api/urls.py
sop_migration/api/views.py
sop_migration/api/__pycache__/__init__.cpython-312.pyc
sop_migration/api/__pycache__/serializers.cpython-312.pyc
sop_migration/api/__pycache__/urls.cpython-312.pyc
sop_migration/api/__pycache__/views.cpython-312.pyc
sop_migration/migrations/0001_initial.py
sop_migration/migrations/__init__.py
sop_migration/migrations/__pycache__/0001_initial.cpython-312.pyc
sop_migration/migrations/__pycache__/__init__.cpython-312.pyc
sop_migration/templates/sop_migration/button.html
sop_migration/templates/sop_migration/panel.html
sop_migration/templates/sop_migration/sopmigration.html
sop_migration-0.0.7.dist-info/METADATA
sop_migration-0.0.7.dist-info/WHEEL
sop_migration-0.0.7.dist-info/top_level.txt
sop_migration-0.0.7.dist-info/RECORD
