Metadata-Version: 2.1
Name: sop-migration
Version: 0.0.7
Summary: Pin your migrations to any NetBox model instance
Author: Leorevoir
Author-email: leo.quinzler@epitech.eu
Classifier: Framework :: Django
Classifier: Programming Language :: Python :: 3
